jobmon/client/__init__.py
jobmon/client/api.py
jobmon/client/array.py
jobmon/client/attributes.py
jobmon/client/cli.py
jobmon/client/dag.py
jobmon/client/logging.py
jobmon/client/node.py
jobmon/client/py.typed
jobmon/client/status_commands.py
jobmon/client/task.py
jobmon/client/task_resources.py
jobmon/client/task_template.py
jobmon/client/task_template_version.py
jobmon/client/tool.py
jobmon/client/tool_version.py
jobmon/client/units.py
jobmon/client/workflow.py
jobmon/client/workflow_run.py
jobmon/client/swarm/__init__.py
jobmon/client/swarm/swarm_array.py
jobmon/client/swarm/swarm_task.py
jobmon/client/swarm/workflow_run.py
jobmon_client-3.3.0.dist-info/METADATA
jobmon_client-3.3.0.dist-info/WHEEL
jobmon_client-3.3.0.dist-info/entry_points.txt
jobmon_client-3.3.0.dist-info/top_level.txt
jobmon_client-3.3.0.dist-info/RECORD
