Metadata-Version: 2.1
Name: jobmon_client
Version: 3.3.0
Summary: A dependency management utility with retires and resource management for HPC computation.
Classifier: Programming Language :: Python :: 3.9
Classifier: Programming Language :: Python :: 3.10
Classifier: Programming Language :: Python :: 3.11
Classifier: Programming Language :: Python :: 3.12
Requires-Python: >=3.9
Requires-Dist: jobmon-core
Requires-Dist: numpy
Requires-Dist: pandas
Requires-Dist: pyyaml
Requires-Dist: tabulate
Provides-Extra: ihme
Requires-Dist: jobmon-installer-ihme ; extra == 'ihme'
Provides-Extra: server
Requires-Dist: jobmon-server ; extra == 'server'
